LICENSE
README.md
setup.py
geoip2fast/__init__.py
geoip2fast/geoip2dat.py
geoip2fast/geoip2fast-asn-ipv6.dat.gz
geoip2fast/geoip2fast-asn.dat.gz
geoip2fast/geoip2fast-ipv6.dat.gz
geoip2fast/geoip2fast.dat.gz
geoip2fast/geoip2fast.py
geoip2fast.egg-info/PKG-INFO
geoip2fast.egg-info/SOURCES.txt
geoip2fast.egg-info/dependency_links.txt
geoip2fast.egg-info/entry_points.txt
geoip2fast.egg-info/not-zip-safe
geoip2fast.egg-info/top_level.txt
geoip2fast/tests/compare_with_mmdb.py
geoip2fast/tests/coverage_test.py
geoip2fast/tests/geoip2fast_test.py
geoip2fast/tests/random_test.py
geoip2fast/tests/speed_test.py