Metadata-Version: 2.1
Name: geoip2fast
Version: 1.2.1
Summary: GeoIP2Fast is the fastest GeoIP2 country/city/asn lookup library that supports IPv4 and IPv6. A search takes less than 0.00003 seconds. It has its own data file updated twice a week with Maxmind-Geolite2-CSV, supports IPv4/IPv6 and is Pure Python!
Home-page: https://github.com/rabuchaim/geoip2fast
Author: Ricardo Abuchaim
Author-email: ricardoabuchaim@gmail.com
Maintainer: Ricardo Abuchaim
Maintainer-email: ricardoabuchaim@gmail.com
License: MIT
Project-URL: Issue Tracker, https://github.com/rabuchaim/geoip2fast/issues
Project-URL: Source code, https://github.com/rabuchaim/geoip2fast
Project-URL: Latest DAT files, https://github.com/rabuchaim/geoip2fast/releases/latest
Project-URL: Legacy v1.1.X DAT files, https://github.com/rabuchaim/geoip2fast/releases/tag/LEGACY
Keywords: geoip,geoip2,geolite2,maxmind,geoip2fast,geolocation,geolocalization,geo ip,ipaddress,ip,geo,ipv4,ipv6,pure-python,purepython,pure python,geoiptofast,geoiptoofast,geoip2dat,mmdb,tools
Classifier: Development Status :: 5 - Production/Stable
Classifier: Topic :: Security
Classifier: Topic :: Internet
Classifier: Topic :: Internet :: Finger
Classifier: Topic :: Scientific/Engineering
Classifier: Topic :: System :: Monitoring
Classifier: Topic :: System :: Networking
Classifier: Topic :: System :: Systems Administration
Classifier: Topic :: Software Development :: Libraries
Classifier: Topic :: Software Development :: Libraries :: Python Modules
Classifier: Topic :: Software Development :: Localization
Classifier: Topic :: Utilities
Classifier: Intended Audience :: Developers
Classifier: Intended Audience :: Information Technology
Classifier: Intended Audience :: System Administrators
Classifier: Operating System :: MacOS
Classifier: Operating System :: Microsoft :: Windows :: Windows 10
Classifier: Operating System :: Microsoft :: Windows :: Windows 11
Classifier: Operating System :: Unix
Classifier: Operating System :: POSIX
Classifier: Operating System :: POSIX :: Linux
Classifier: Operating System :: POSIX :: BSD
Classifier: Operating System :: POSIX :: BSD :: FreeBSD
Classifier: Programming Language :: Python
Classifier: Programming Language :: Python :: 3
Classifier: Programming Language :: Python :: 3.7
Classifier: Programming Language :: Python :: 3.8
Classifier: Programming Language :: Python :: 3.9
Classifier: Programming Language :: Python :: 3.10
Classifier: Programming Language :: Python :: 3.11
Classifier: Programming Language :: Python :: 3.12
Classifier: Programming Language :: Python :: 3.13
Classifier: Programming Language :: Python :: Implementation :: PyPy
Classifier: License :: OSI Approved :: MIT License
Requires-Python: >=3.7
License-File: LICENSE
